django_email_learning/__init__.py
django_email_learning/admin.py
django_email_learning/apps.py
django_email_learning/decorators.py
django_email_learning/jobs/__init__.py
django_email_learning/jobs/api/__init__.py
django_email_learning/jobs/api/urls.py
django_email_learning/jobs/api/views.py
django_email_learning/jobs/deliver_contents_job.py
django_email_learning/management/__init__.py
django_email_learning/management/commands/__init__py
django_email_learning/management/commands/deliver_contents.py
django_email_learning/migrations/0001_initial.py
django_email_learning/migrations/0002_apikey.py
django_email_learning/migrations/0003_apikey_salt_imapconnection_salt.py
django_email_learning/migrations/0004_jobexecution_alter_apikey_salt_and_more.py
django_email_learning/migrations/0005_course_image_alter_apikey_salt_and_more.py
django_email_learning/migrations/__init__.py
django_email_learning/models.py
django_email_learning/personalised/api/__init__.py
django_email_learning/personalised/api/serializers.py
django_email_learning/personalised/api/urls.py
django_email_learning/personalised/api/views.py
django_email_learning/personalised/serializers.py
django_email_learning/personalised/urls.py
django_email_learning/personalised/views.py
django_email_learning/platform/__init__.py
django_email_learning/platform/api/__init__.py
django_email_learning/platform/api/pagniated_api_mixin.py
django_email_learning/platform/api/serializers.py
django_email_learning/platform/api/urls.py
django_email_learning/platform/api/views.py
django_email_learning/platform/urls.py
django_email_learning/platform/views.py
django_email_learning/ports/__init__.py
django_email_learning/ports/delivery_queue_protocol.py
django_email_learning/ports/email_sender_protocol.py
django_email_learning/public/__init__.py
django_email_learning/public/api/__init__.py
django_email_learning/public/api/serializers.py
django_email_learning/public/api/urls.py
django_email_learning/public/api/views.py
django_email_learning-0.1.26.dist-info/METADATA
django_email_learning-0.1.26.dist-info/WHEEL
django_email_learning-0.1.26.dist-info/licenses/LICENSE
django_email_learning-0.1.26.dist-info/RECORD
