Metadata-Version: 2.4
Name: django-email-learning
Version: 0.1.26
Summary: A platform for creating and delivering  learning materials via email within a Django application. It provides tools for content management, user role-based administration, and scheduler integration for automated content delivery.
License-Expression: BSD-3-Clause
License-File: LICENSE
Author: Payam Najafizadeh
Author-email: payam.nj@gmail.com
Requires-Python: >=3.10
Classifier: Development Status :: 3 - Alpha
Classifier: Framework :: Django
Classifier: Framework :: Django :: 5.0
Classifier: Framework :: Django :: 6.0
Classifier: Intended Audience :: Developers
Classifier: License :: OSI Approved :: BSD License
Classifier: Programming Language :: Python :: 3
Classifier: Programming Language :: Python :: 3.11
Classifier: Programming Language :: Python :: 3.12
Classifier: Programming Language :: Python :: 3.13
Classifier: Programming Language :: Python :: 3.14
Classifier: Topic :: Education
Requires-Dist: cryptography (>=46.0.3,<47.0.0)
Requires-Dist: pillow (>=12.0.0,<13.0.0)
Requires-Dist: pydantic (>=2.12.4,<3.0.0)
Requires-Dist: pyjwt (>=2.10.1,<3.0.0)
Project-URL: Repository, https://github.com/AvaCodeSolutions/django-email-learning
